sql_profiling/__init__.py
sql_profiling/__main__.py
sql_profiling-1.2.0.dist-info/LICENSE
sql_profiling-1.2.0.dist-info/METADATA
sql_profiling-1.2.0.dist-info/WHEEL
sql_profiling-1.2.0.dist-info/top_level.txt
sql_profiling-1.2.0.dist-info/RECORD
