Metadata-Version: 2.1
Name: sql-profiling
Version: 1.2.0
Summary: Automatically profile table by name, source database type, and DSN.
Home-page: UNKNOWN
Author: Dan Eschman
Author-email: deschman007@gmail.com
License: UNKNOWN
Platform: UNKNOWN
Classifier: Development Status :: 4 - Beta
Classifier: Intended Audience :: Developers
Classifier: Natural Language :: English
Classifier: Programming Language :: Python :: 3
Classifier: Topic :: Database
Requires-Python: >=3.8
Requires-Dist: pytest
Requires-Dist: sqlalchemy
Requires-Dist: pyodbc
Requires-Dist: pandas
Requires-Dist: dask[distributed]
Requires-Dist: modin
Requires-Dist: pandas-profiling
